catie/__init__.py
catie/metrics.py
catie-2.2.0.dist-info/LICENSE
catie-2.2.0.dist-info/METADATA
catie-2.2.0.dist-info/WHEEL
catie-2.2.0.dist-info/top_level.txt
catie-2.2.0.dist-info/RECORD
