Metadata-Version: 2.1
Name: catie
Version: 2.2.0
Summary: Tools to compute cohort-attention tied entropy, including CATSensitivity, CATSpecificity, and their combination - CATmean
Home-page: https://github.com/jianfeizhang/catie
Author: Jianfei Zhang
Author-email: jianfei.zhang@live.ca
License: UNKNOWN
Platform: UNKNOWN
Classifier: Programming Language :: Python :: 3
Classifier: License :: OSI Approved :: MIT License
Classifier: Operating System :: OS Independent
Requires-Python: >=3.7
License-File: LICENSE
